README.md
setup.cfg
setup.py
compound_types/__init__.py
compound_types/arrays.py
compound_types/type_checks.py
compound_types.egg-info/PKG-INFO
compound_types.egg-info/SOURCES.txt
compound_types.egg-info/dependency_links.txt
compound_types.egg-info/top_level.txt
compound_types/built_ins/__init__.py
compound_types/built_ins/iterables.py
compound_types/built_ins/lists.py
compound_types/built_ins/pairs.py
compound_types/built_ins/single_or_iterable.py
compound_types/built_ins/single_or_list.py
compound_types/built_ins/sized_iterables.py
compound_types/built_ins/sizeds.py
compound_types/built_ins/unions.py