Metadata-Version: 1.1
Name: compound-types
Version: 0.0.8
Summary: Python package of compound types.
Home-page: https://github.com/vahndi/compound-types
Author: Vahndi Minah
Author-email: UNKNOWN
License: MIT
Platform: UNKNOWN
Classifier: Development Status :: 3 - Alpha
Classifier: Intended Audience :: Developers
Classifier: Topic :: Software Development
Classifier: License :: OSI Approved :: MIT License
Classifier: Programming Language :: Python :: 3
